README.rst
setup.py
mirrors/__init__.py
mirrors/admin.py
mirrors/apps.py
mirrors/components.py
mirrors/exceptions.py
mirrors/middleware.py
mirrors/models.py
mirrors/serializers.py
mirrors/urls.py
mirrors/views.py
mirrors.egg-info/PKG-INFO
mirrors.egg-info/SOURCES.txt
mirrors.egg-info/dependency_links.txt
mirrors.egg-info/requires.txt
mirrors.egg-info/top_level.txt
mirrors/migrations/0001_initial.py
mirrors/migrations/0002_auto_20140609_1823.py
mirrors/migrations/0003_componentrevision_version.py
mirrors/migrations/0004_auto_20140609_1943.py
mirrors/migrations/0005_auto_20140609_2310.py
mirrors/migrations/0006_auto_20140609_2314.py
mirrors/migrations/0007_componentlock.py
mirrors/migrations/0008_auto_20140814_2150.py
mirrors/migrations/0009_auto_20140825_2229.py
mirrors/migrations/0010_auto_20140827_2021.py
mirrors/migrations/0011_auto_20141103_2224.py
mirrors/migrations/0012_auto_20150113_2208.py
mirrors/migrations/0013_auto_20150127_0019.py
mirrors/migrations/0014_auto_20150224_2252.py
mirrors/migrations/0015_auto_20150317_2329.py
mirrors/migrations/0016_auto_20150319_1940.py
mirrors/migrations/0017_auto_20150420_2140.py
mirrors/migrations/__init__.py
mirrors/tests/__init__.py
mirrors/tests/test_auth.py
mirrors/tests/test_autocomplete.py
mirrors/tests/test_components.py
mirrors/tests/test_models.py
mirrors/tests/test_serializers.py
mirrors/tests/test_views.py
mirrors_publisher/__init__.py
mirrors_publisher/backend_adapters.py
mirrors_publisher/exceptions.py
mirrors_publisher/models.py
mirrors_publisher/filters/__init__.py
mirrors_publisher/management/__init__.py
mirrors_publisher/management/commands/__init__.py
mirrors_publisher/management/commands/publish.py
mirrors_publisher/migrations/0001_initial.py
mirrors_publisher/migrations/__init__.py
mirrors_publisher/tests/__init__.py
mirrors_publisher/tests/test_backend_adapters.py
mirrors_publisher/tests/test_commands.py
mirrors_publisher/tests/test_filters.py