Metadata-Version: 1.0
Name: mirrors
Version: 0.0.1-1
Summary: Backend server for the smokejs project
Home-page: UNKNOWN
Author: Mikela Clemmons, Jon Friedman, Cameron Adamez
Author-email: mclemmons@motherjones.com, jfriedman@motherjones.com, cadamez@motherjones.com
License: MIT
Platform: UNKNOWN
